README.md
setup.py
Chapter_2_Core_Python/Chapter_2_Case_Study/rate_table/RateTable.py
Chapter_2_Core_Python/Chapter_2_Case_Study/rate_table/TestRateTables.py
Chapter_2_Core_Python/Chapter_2_Case_Study/rate_table/__init__.py
actuary/__init__.py
actuary.egg-info/PKG-INFO
actuary.egg-info/SOURCES.txt
actuary.egg-info/dependency_links.txt
actuary.egg-info/top_level.txt
actuary/regression/__init__.py
actuary/regression/linear_regression.py
actuary/utils/__init__.py
actuary/utils/formatting.py