Metadata-Version: 1.0
Name: actuary
Version: 0.1
Summary: This is an actuarial toolkit as introduced by three Actex webinars on Python for Actuaries
Home-page: https://github.com/validatehealth/actuary
Author: Andrew Webster
Author-email: andrew.webster@validatehealth.com
License: MIT
Platform: UNKNOWN
